grugstream/__init__.py
grugstream/acknowledgement.py
grugstream/core.py
grugstream/exceptions.py
grugstream/subscriber.py
grugstream-0.0.17.dist-info/METADATA
grugstream-0.0.17.dist-info/WHEEL
grugstream-0.0.17.dist-info/RECORD
