Metadata-Version: 2.1
Name: grugstream
Version: 0.0.17
Summary: The grugstream library provides an easy way to work with asynchronous/ reactive / streaming programming.
Home-page: https://github.com/thejaminator/grugstream
License: MIT
Author: James Chua
Author-email: chuajamessh@gmail.com
Requires-Python: >=3.9,<4.0
Classifier: Development Status :: 2 - Pre-Alpha
Classifier: Intended Audience :: Developers
Classifier: License :: OSI Approved :: MIT License
Classifier: Natural Language :: English
Classifier: Programming Language :: Python :: 3
Classifier: Programming Language :: Python :: 3.9
Classifier: Programming Language :: Python :: 3.10
Classifier: Programming Language :: Python :: 3.11
Classifier: Programming Language :: Python :: 3.12
Requires-Dist: anyio (>=3.3.0,<4.0.0)
Requires-Dist: slist
